llama_index/legacy/BUILD
llama_index/legacy/VERSION
llama_index/legacy/__init__.py
llama_index/legacy/_static/nltk_cache/.gitignore
llama_index/legacy/_static/tiktoken_cache/.gitignore
llama_index/legacy/_static/tiktoken_cache/9b5ad71b2ce5302211f9c61530b329a4922fc6a4
llama_index/legacy/agent/BUILD
llama_index/legacy/agent/__init__.py
llama_index/legacy/agent/custom/BUILD
llama_index/legacy/agent/custom/__init__.py
llama_index/legacy/agent/custom/pipeline_worker.py
llama_index/legacy/agent/custom/simple.py
llama_index/legacy/agent/legacy/BUILD
llama_index/legacy/agent/legacy/__init__.py
llama_index/legacy/agent/legacy/context_retriever_agent.py
llama_index/legacy/agent/legacy/openai_agent.py
llama_index/legacy/agent/legacy/react/BUILD
llama_index/legacy/agent/legacy/react/__init__.py
llama_index/legacy/agent/legacy/react/base.py
llama_index/legacy/agent/legacy/retriever_openai_agent.py
llama_index/legacy/agent/openai/BUILD
llama_index/legacy/agent/openai/__init__.py
llama_index/legacy/agent/openai/base.py
llama_index/legacy/agent/openai/step.py
llama_index/legacy/agent/openai/utils.py
llama_index/legacy/agent/openai_assistant_agent.py
llama_index/legacy/agent/react/BUILD
llama_index/legacy/agent/react/__init__.py
llama_index/legacy/agent/react/agent.py
llama_index/legacy/agent/react/base.py
llama_index/legacy/agent/react/formatter.py
llama_index/legacy/agent/react/output_parser.py
llama_index/legacy/agent/react/prompts.py
llama_index/legacy/agent/react/step.py
llama_index/legacy/agent/react/types.py
llama_index/legacy/agent/react_multimodal/BUILD
llama_index/legacy/agent/react_multimodal/__init__.py
llama_index/legacy/agent/react_multimodal/prompts.py
llama_index/legacy/agent/react_multimodal/step.py
llama_index/legacy/agent/runner/BUILD
llama_index/legacy/agent/runner/__init__.py
llama_index/legacy/agent/runner/base.py
llama_index/legacy/agent/runner/parallel.py
llama_index/legacy/agent/types.py
llama_index/legacy/agent/utils.py
llama_index/legacy/async_utils.py
llama_index_legacy-0.9.46.dist-info/METADATA
llama_index_legacy-0.9.46.dist-info/WHEEL
llama_index_legacy-0.9.46.dist-info/entry_points.txt
llama_index_legacy-0.9.46.dist-info/RECORD
