Metadata-Version: 2.1
Name: llama-index-legacy
Version: 0.9.46
Summary: Interface between LLMs and your data
Home-page: https://llamaindex.ai
License: MIT
Keywords: LLM,NLP,RAG,data,devtools,index,retrieval
Author: Jerry Liu
Author-email: jerry@llamaindex.ai
Maintainer: Andrei Fajardo
Maintainer-email: andrei@runllama.ai
Requires-Python: >=3.8.1,<4.0
Classifier: License :: OSI Approved :: MIT License
Classifier: Programming Language :: Python :: 3
Classifier: Programming Language :: Python :: 3.9
Classifier: Programming Language :: Python :: 3.10
Classifier: Programming Language :: Python :: 3.11
Classifier: Programming Language :: Python :: 3.12
Classifier: Topic :: Scientific/Engineering :: Artificial Intelligence
Classifier: Topic :: Software Development :: Libraries :: Application Frameworks
Classifier: Topic :: Software Development :: Libraries :: Python Modules
Provides-Extra: gradientai
Provides-Extra: html
Provides-Extra: langchain
Provides-Extra: local-models
Provides-Extra: postgres
Provides-Extra: query-tools
Requires-Dist: SQLAlchemy[asyncio] (>=1.4.49)
Requires-Dist: aiohttp (>=3.8.6,<4.0.0)
Requires-Dist: asyncpg (>=0.28.0,<0.29.0) ; extra == "postgres"
Requires-Dist: beautifulsoup4 (>=4.12.2,<5.0.0) ; extra == "html"
Requires-Dist: dataclasses-json
Requires-Dist: deprecated (>=1.2.9.3)
Requires-Dist: dirtyjson (>=1.0.8,<2.0.0)
Requires-Dist: fsspec (>=2023.5.0)
Requires-Dist: gradientai (>=1.4.0) ; extra == "gradientai"
Requires-Dist: guidance (>=0.0.64,<0.0.65) ; extra == "query-tools"
Requires-Dist: httpx
Requires-Dist: jsonpath-ng (>=1.6.0,<2.0.0) ; extra == "query-tools"
Requires-Dist: langchain (>=0.0.303) ; extra == "langchain"
Requires-Dist: lm-format-enforcer (>=0.4.3,<0.5.0) ; extra == "query-tools"
Requires-Dist: nest-asyncio (>=1.5.8,<2.0.0)
Requires-Dist: networkx (>=3.0)
Requires-Dist: nltk (>=3.8.1,<4.0.0)
Requires-Dist: numpy
Requires-Dist: openai (>=1.1.0)
Requires-Dist: optimum[onnxruntime] (>=1.13.2,<2.0.0) ; extra == "local-models"
Requires-Dist: pandas
Requires-Dist: pgvector (>=0.1.0,<0.2.0) ; extra == "postgres"
Requires-Dist: psycopg2-binary (>=2.9.9,<3.0.0) ; extra == "postgres"
Requires-Dist: rank-bm25 (>=0.2.2,<0.3.0) ; extra == "query-tools"
Requires-Dist: requests (>=2.31.0)
Requires-Dist: scikit-learn ; extra == "query-tools"
Requires-Dist: sentencepiece (>=0.1.99,<0.2.0) ; extra == "local-models"
Requires-Dist: spacy (>=3.7.1,<4.0.0) ; extra == "query-tools"
Requires-Dist: tenacity (>=8.2.0,<9.0.0)
Requires-Dist: tiktoken (>=0.3.3)
Requires-Dist: transformers[torch] (>=4.33.1,<5.0.0) ; extra == "local-models"
Requires-Dist: typing-extensions (>=4.5.0)
Requires-Dist: typing-inspect (>=0.8.0)
Project-URL: Documentation, https://docs.llamaindex.ai/en/stable/
Project-URL: Repository, https://github.com/run-llama/llama_index
